winsddl/__init__.py
winsddl/constants.py
winsddl-0.1.0.dist-info/WHEEL
winsddl-0.1.0.dist-info/METADATA
winsddl-0.1.0.dist-info/RECORD
