Metadata-Version: 2.3
Name: winsddl
Version: 0.1.0
Summary: A comprehensive Python parser for SDDL strings, supporting multiple objects.
Author: CobblePot59
License: GPLv3
Classifier: Programming Language :: Python :: 3
Classifier: License :: OSI Approved :: GNU General Public License v3 (GPLv3)
Classifier: Operating System :: OS Independent
Requires-Dist: rich>=14.3.0
Requires-Python: >=3.10
Project-URL: Repository, https://github.com/CobblePot59/WinSDDL
